itkdb_browser/__init__.py
itkdb_browser/__main__.py
itkdb_browser/_version.py
itkdb_browser/_version.pyi
itkdb_browser/draggable_list_view.py
itkdb_browser/py.typed
itkdb_browser/tui.css
itkdb_browser/tui.py
itkdb_browser-0.2.0.dist-info/METADATA
itkdb_browser-0.2.0.dist-info/WHEEL
itkdb_browser-0.2.0.dist-info/entry_points.txt
itkdb_browser-0.2.0.dist-info/licenses/LICENSE
itkdb_browser-0.2.0.dist-info/RECORD
