Metadata-Version: 2.1
Name: itkdb_browser
Version: 0.2.0
Summary: TUI browser for ITk Production DB using itkdb
Project-URL: Homepage, https://github.com/kratsg/itkdb-browser
Project-URL: Bug Tracker, https://github.com/kratsg/itkdb-browser/issues
Project-URL: Discussions, https://github.com/kratsg/itkdb-browser/discussions
Project-URL: Changelog, https://github.com/kratsg/itkdb-browser/releases
Author-email: Giordon Stark <kratsg@gmail.com>
License-File: LICENSE
Classifier: Development Status :: 1 - Planning
Classifier: Intended Audience :: Developers
Classifier: Intended Audience :: Science/Research
Classifier: License :: OSI Approved :: BSD License
Classifier: Operating System :: OS Independent
Classifier: Programming Language :: Python
Classifier: Programming Language :: Python :: 3
Classifier: Programming Language :: Python :: 3 :: Only
Classifier: Programming Language :: Python :: 3.8
Classifier: Programming Language :: Python :: 3.9
Classifier: Programming Language :: Python :: 3.10
Classifier: Programming Language :: Python :: 3.11
Classifier: Topic :: Scientific/Engineering
Classifier: Typing :: Typed
Requires-Python: >=3.8
Requires-Dist: itkdb>=0.4.13
Requires-Dist: rich>=13.0.0
Requires-Dist: textual>=0.40.0
Requires-Dist: typer
Provides-Extra: dev
Requires-Dist: pytest-cov>=3; extra == 'dev'
Requires-Dist: pytest>=6; extra == 'dev'
Provides-Extra: docs
Requires-Dist: myst-parser>=0.13; extra == 'docs'
Requires-Dist: sphinx-book-theme>=0.1.0; extra == 'docs'
Requires-Dist: sphinx-copybutton; extra == 'docs'
Requires-Dist: sphinx>=4.0; extra == 'docs'
Provides-Extra: test
Requires-Dist: pytest-cov>=3; extra == 'test'
Requires-Dist: pytest>=6; extra == 'test'
